cli/__init__.py
cli/workflow.py
core/__init__.py
core/analyzer.py
core/compressor.py
core/metadata.py
core/types.py
core/metadata/__init__.py
core/metadata/base_handler.py
core/metadata/bnf_handler.py
core/metadata/xmp_utils.py
jp2forge-0.9.7.dist-info/licenses/LICENSE
reporting/__init__.py
reporting/reports.py
utils/__init__.py
utils/benchmark.py
utils/color_profiles.py
utils/image.py
utils/io.py
utils/logging_config.py
utils/profiling.py
utils/resource_monitor.py
utils/validation.py
utils/config/__init__.py
utils/config/config_manager.py
utils/config/config_schema.py
utils/imaging/__init__.py
utils/imaging/memory_estimator.py
utils/imaging/streaming_processor.py
utils/parallel/__init__.py
utils/parallel/adaptive_pool.py
utils/parallel/progress_tracker.py
utils/parallel/resource_monitor.py
utils/tools/__init__.py
utils/tools/exiftool.py
utils/tools/jpylyzer_tool.py
utils/tools/tool_manager.py
utils/xml/__init__.py
utils/xml/namespace_registry.py
utils/xml/xmp_manager.py
workflow/__init__.py
workflow/base.py
workflow/parallel.py
workflow/standard.py
workflow/utils.py
jp2forge-0.9.7.dist-info/METADATA
jp2forge-0.9.7.dist-info/WHEEL
jp2forge-0.9.7.dist-info/entry_points.txt
jp2forge-0.9.7.dist-info/top_level.txt
jp2forge-0.9.7.dist-info/RECORD
