Metadata-Version: 2.4
Name: jp2forge
Version: 0.9.7
Summary: A comprehensive JPEG2000 processing tool with BnF compatibility
Home-page: https://github.com/xy-liao/jp2forge
Author: xy-liao
Project-URL: Bug Tracker, https://github.com/xy-liao/jp2forge/issues
Project-URL: Documentation, https://github.com/xy-liao/jp2forge/tree/main/docs
Classifier: Programming Language :: Python :: 3
Classifier: License :: OSI Approved :: MIT License
Classifier: Operating System :: OS Independent
Classifier: Topic :: Multimedia :: Graphics :: Graphics Conversion
Classifier: Intended Audience :: Science/Research
Classifier: Intended Audience :: Education
Requires-Python: >=3.8
License-File: LICENSE
Requires-Dist: numpy>=1.20.0
Requires-Dist: pillow>=9.0.0
Requires-Dist: psutil>=5.8.0
Requires-Dist: structlog>=21.1.0
Requires-Dist: lxml>=4.9.0
Requires-Dist: pyyaml>=6.0
Requires-Dist: jpylyzer>=2.2.0
Requires-Dist: matplotlib>=3.9.0
Requires-Dist: pandas>=2.2.0
Dynamic: author
Dynamic: classifier
Dynamic: description
Dynamic: description-content-type
Dynamic: home-page
Dynamic: license-file
Dynamic: project-url
Dynamic: requires-dist
Dynamic: requires-python
Dynamic: summary
